sqlalchemy_neo4j/__init__.py
sqlalchemy_neo4j/interop.py
sqlalchemy_neo4j/jdbc.py
sqlalchemy_neo4j/neo4j_cypher.py
sqlalchemy_neo4j/neo4j_jdbc.py
sqlalchemy_neo4j-0.2.dev0.dist-info/LICENSE
sqlalchemy_neo4j-0.2.dev0.dist-info/WHEEL
sqlalchemy_neo4j-0.2.dev0.dist-info/METADATA
sqlalchemy_neo4j-0.2.dev0.dist-info/RECORD
