Metadata-Version: 2.1
Name: sqlalchemy-neo4j
Version: 0.2.dev0
Summary: SQL Alchemy dialect for Neo4j
Home-page: https://github.com/bbenzikry/sqlalchemy-neo4j
Keywords: neo4j,sqlalchemy,graph,database
Author: Beni Ben Zikry
Requires-Python: >=3.6.2,<4.0.0
Classifier: Development Status :: 2 - Pre-Alpha
Classifier: Intended Audience :: Developers
Classifier: Operating System :: OS Independent
Classifier: Programming Language :: Python
Classifier: Programming Language :: Python :: 3
Classifier: Programming Language :: Python :: 3.7
Classifier: Programming Language :: Python :: 3.8
Classifier: Programming Language :: Python :: 3.9
Classifier: Programming Language :: Python :: Implementation :: CPython
Classifier: Topic :: Database :: Front-Ends
Requires-Dist: jaydebeapi
Requires-Dist: jpype1
Requires-Dist: sqlalchemy (>=1.0,<1.4)
